odoo10_addon_website_event_filter_selector-10.0.1.0.0-py2.7-nspkg.pth
odoo/addons/website_event_filter_selector/README.rst
odoo/addons/website_event_filter_selector/__init__.py
odoo/addons/website_event_filter_selector/__manifest__.py
odoo/addons/website_event_filter_selector/controllers/__init__.py
odoo/addons/website_event_filter_selector/controllers/main.py
odoo/addons/website_event_filter_selector/demo/assets.xml
odoo/addons/website_event_filter_selector/i18n/de.po
odoo/addons/website_event_filter_selector/i18n/es.po
odoo/addons/website_event_filter_selector/images/all.png
odoo/addons/website_event_filter_selector/images/choose.png
odoo/addons/website_event_filter_selector/models/__init__.py
odoo/addons/website_event_filter_selector/models/event.py
odoo/addons/website_event_filter_selector/static/description/icon.png
odoo/addons/website_event_filter_selector/static/src/js/website_event_filter_selector.js
odoo/addons/website_event_filter_selector/static/src/js/website_event_filter_selector.tour.js
odoo/addons/website_event_filter_selector/templates/assets.xml
odoo/addons/website_event_filter_selector/templates/event.xml
odoo/addons/website_event_filter_selector/tests/__init__.py
odoo/addons/website_event_filter_selector/tests/test_ui.py
odoo10_addon_website_event_filter_selector-10.0.1.0.0.dist-info/DESCRIPTION.rst
odoo10_addon_website_event_filter_selector-10.0.1.0.0.dist-info/METADATA
odoo10_addon_website_event_filter_selector-10.0.1.0.0.dist-info/RECORD
odoo10_addon_website_event_filter_selector-10.0.1.0.0.dist-info/WHEEL
odoo10_addon_website_event_filter_selector-10.0.1.0.0.dist-info/metadata.json
odoo10_addon_website_event_filter_selector-10.0.1.0.0.dist-info/namespace_packages.txt
odoo10_addon_website_event_filter_selector-10.0.1.0.0.dist-info/top_level.txt
