Metadata-Version: 2.0
Name: odoo10-addon-website-event-filter-selector
Version: 10.0.1.0.0
Summary: Add a customizable top area to filter events with selectors
Home-page: https://www.tecnativa.com
Author: Antiun Ingeniería S.L., Tecnativa, Odoo Community Association (OCA)
Author-email: support@odoo-community.org
License: LGPL-3
Platform: UNKNOWN
Classifier: Programming Language :: Python :: 2.7
Classifier: Framework :: Odoo
Classifier: License :: OSI Approved :: GNU Lesser General Public License v3 (LGPLv3)
Requires-Dist: odoo (<10.1dev,>=10.0)
